relation_app/Schema.py
relation_app/Service.py
relation_app/__init__.py
relationapp-0.0.2.dist-info/METADATA
relationapp-0.0.2.dist-info/WHEEL
relationapp-0.0.2.dist-info/top_level.txt
relationapp-0.0.2.dist-info/RECORD
